setup.py
ripsaw/__init__.py
ripsaw/monitor.py
ripsaw/new.py
ripsaw/new_monitor.py
ripsaw/reporter.py
ripsaw/time.py
ripsaw/trigger.py
ripsaw.egg-info/PKG-INFO
ripsaw.egg-info/SOURCES.txt
ripsaw.egg-info/dependency_links.txt
ripsaw.egg-info/requires.txt
ripsaw.egg-info/top_level.txt
ripsaw.egg-info/zip-safe