Metadata-Version: 1.1
Name: ripsaw
Version: 0.0.7
Summary: cut logs into bits
Home-page: https://github.com/philipov/ripsaw
Author: Philip Loguinov
Author-email: philipov@gmail.com
License: MIT License
Platform: UNKNOWN
Classifier: Environment :: Console
Classifier: Environment :: Other Environment
Classifier: Intended Audience :: Information Technology
Classifier: Intended Audience :: Developers
Classifier: Intended Audience :: System Administrators
Classifier: Intended Audience :: End Users/Desktop
Classifier: Intended Audience :: Customer Service
Classifier: License :: Other/Proprietary License
Classifier: Operating System :: Microsoft :: Windows :: Windows 7
Classifier: Operating System :: POSIX :: Linux
Classifier: Programming Language :: Python :: 3.6
